{
  "entries": {
    "tap": {
      "homebrew/bundle": {
        "revision": "491e2fbd399d1467f3cfab7fe4c4f07b17bfab7f"
      },
      "homebrew/cask": {
        "revision": "a19fd996a1f7bc52e53b7850f1daa072798ab17e"
      },
      "homebrew/cask-versions": {
        "revision": "30d7d8efe332cb7b2e68b3d98fe2cb6b12d7b4a7"
      },
      "homebrew/core": {
        "revision": "92825ca1a32fcc1ce50ba280ecd87ec3f31809f1"
      }
    },
    "brew": {
      "ansible": {
        "version": "2.9.2",
        "bottle": {
          "cellar": ":any",
          "prefix": "/usr/local",
          "files": {
            "catalina": {
              "url": "https://homebrew.bintray.com/bottles/ansible-2.9.2.catalina.bottle.1.tar.gz",
              "sha256": "ce13d36d45f503c545b18ea243763c87de6f51dbc2cd8bb5be8c0a9209931a59"
            },
            "mojave": {
              "url": "https://homebrew.bintray.com/bottles/ansible-2.9.2.mojave.bottle.1.tar.gz",
              "sha256": "3aa1c3c50b68e086799fa0e775ad4039aede3697cbba99b9c336e6cc7eeb8231"
            },
            "high_sierra": {
              "url": "https://homebrew.bintray.com/bottles/ansible-2.9.2.high_sierra.bottle.1.tar.gz",
              "sha256": "56ddc3764ecfb4ca657ebb8f9f8b6e986ed580c86508edc1d19ebb1954025df8"
            }
          }
        }
      },
      "awscli": {
        "version": "1.16.300",
        "bottle": {
          "cellar": ":any_skip_relocation",
          "prefix": "/usr/local",
          "files": {
            "catalina": {
              "url": "https://homebrew.bintray.com/bottles/awscli-1.16.300.catalina.bottle.tar.gz",
              "sha256": "1bdb37360ead0f8dd3a9d4982cf4cf95a9f9bee6faf161a91ef3ec1d0496b342"
            },
            "mojave": {
              "url": "https://homebrew.bintray.com/bottles/awscli-1.16.300.mojave.bottle.tar.gz",
              "sha256": "c5f6c1522d49507173fd2d7c883e9fb828438ef04f1cd837d5decd12bd0592ac"
            },
            "high_sierra": {
              "url": "https://homebrew.bintray.com/bottles/awscli-1.16.300.high_sierra.bottle.tar.gz",
              "sha256": "96a315b11b9e3c4acdf5d5a74be281e9d66a6262bbb51b5c8d6b06741375ce7e"
            }
          }
        }
      },
      "circleci": {
        "version": "0.1.5879",
        "bottle": {
          "cellar": ":any_skip_relocation",
          "prefix": "/usr/local",
          "files": {
            "catalina": {
              "url": "https://homebrew.bintray.com/bottles/circleci-0.1.5879.catalina.bottle.tar.gz",
              "sha256": "6c70e1810214aac26798cfc5ac8734fbecae1baee3af9af8b5f45dedca66d30c"
            },
            "mojave": {
              "url": "https://homebrew.bintray.com/bottles/circleci-0.1.5879.mojave.bottle.tar.gz",
              "sha256": "48adff67b7d69ed1a6656a754e754e8cae67ce4ec7929a805c405bbce89eabc9"
            },
            "high_sierra": {
              "url": "https://homebrew.bintray.com/bottles/circleci-0.1.5879.high_sierra.bottle.tar.gz",
              "sha256": "b82e42bd9c5026de007fbb5c684e8fd2875db82c25a935b9e22ff5563d94217f"
            },
            "sierra": {
              "url": "https://homebrew.bintray.com/bottles/circleci-0.1.5879.sierra.bottle.tar.gz",
              "sha256": "37088c6cc436902542b008a3f78aad369f7a199f0d24cb2b3573d0e95a795256"
            }
          }
        }
      },
      "cmake": {
        "version": "3.16.1",
        "bottle": {
          "cellar": ":any_skip_relocation",
          "prefix": "/usr/local",
          "files": {
            "catalina": {
              "url": "https://homebrew.bintray.com/bottles/cmake-3.16.1.catalina.bottle.tar.gz",
              "sha256": "75a5155277f4a99a4bcd12ca56700abc2054e0dbeb9609c033d090f891a906e6"
            },
            "mojave": {
              "url": "https://homebrew.bintray.com/bottles/cmake-3.16.1.mojave.bottle.tar.gz",
              "sha256": "68e76688af2ffcaa76e59287d7b40ed6970dc57b3268d5886387a77deaf5fcde"
            },
            "high_sierra": {
              "url": "https://homebrew.bintray.com/bottles/cmake-3.16.1.high_sierra.bottle.tar.gz",
              "sha256": "f92bf13e0fe260a833b9b1b8fe19f1025a70f6ed43c1f5c07badd70ceb7106b5"
            }
          }
        }
      },
      "cookiecutter": {
        "version": "1.6.0_1",
        "bottle": {
          "cellar": ":any_skip_relocation",
          "prefix": "/usr/local",
          "files": {
            "catalina": {
              "url": "https://homebrew.bintray.com/bottles/cookiecutter-1.6.0_1.catalina.bottle.tar.gz",
              "sha256": "0173a3c2191afae34c5f9a7ddbcee18af474af72a0c6a73550b998d7f4afc15f"
            },
            "mojave": {
              "url": "https://homebrew.bintray.com/bottles/cookiecutter-1.6.0_1.mojave.bottle.tar.gz",
              "sha256": "1e94cf29799e53ebf73c20b1a638f66de638956105e3085df99692d0346c1968"
            },
            "high_sierra": {
              "url": "https://homebrew.bintray.com/bottles/cookiecutter-1.6.0_1.high_sierra.bottle.tar.gz",
              "sha256": "b4934159cb33a5b992acd3b8e579d20b95b2571e8fc8625bb51752d8e6f2a405"
            },
            "sierra": {
              "url": "https://homebrew.bintray.com/bottles/cookiecutter-1.6.0_1.sierra.bottle.tar.gz",
              "sha256": "d8122f6df952099b7cba6d05930a12c1f4ec4c4dca65dfbd2cc9c536edbcc055"
            }
          }
        }
      },
      "coreutils": {
        "version": "8.31",
        "bottle": {
          "cellar": "/usr/local/Cellar",
          "prefix": "/usr/local",
          "files": {
            "catalina": {
              "url": "https://homebrew.bintray.com/bottles/coreutils-8.31.catalina.bottle.1.tar.gz",
              "sha256": "7262e4c76483ea796454db828c25955be1e6b2bc8e056ba1dd6e92bfe1118da5"
            },
            "mojave": {
              "url": "https://homebrew.bintray.com/bottles/coreutils-8.31.mojave.bottle.1.tar.gz",
              "sha256": "05ae58c26a53c2dfa2d9d45943b9d21753eea59609f0a48caa59713d6f6392d7"
            },
            "high_sierra": {
              "url": "https://homebrew.bintray.com/bottles/coreutils-8.31.high_sierra.bottle.1.tar.gz",
              "sha256": "5cba7394f1995fad0f6215a7618f65983dcf84b93b076af18d09354051320fb2"
            }
          }
        }
      },
      "go": {
        "version": "1.13.4",
        "bottle": {
          "cellar": "/usr/local/Cellar",
          "prefix": "/usr/local",
          "files": {
            "catalina": {
              "url": "https://homebrew.bintray.com/bottles/go-1.13.4.catalina.bottle.tar.gz",
              "sha256": "77af3e8081a002c86b4b87ec97dc5dc28cab49704913a4db22ebc7ce838dc6ad"
            },
            "mojave": {
              "url": "https://homebrew.bintray.com/bottles/go-1.13.4.mojave.bottle.tar.gz",
              "sha256": "2fc74073a90a7073dab940868ac23fa6cd465af8a39ed2d882b18d62bec2265f"
            },
            "high_sierra": {
              "url": "https://homebrew.bintray.com/bottles/go-1.13.4.high_sierra.bottle.tar.gz",
              "sha256": "20d5242dbbb08128c254a1cc96f55cfc9add74c9567600dfd9366f3d028f5563"
            }
          }
        }
      },
      "dep": {
        "version": "0.5.4",
        "bottle": {
          "cellar": ":any_skip_relocation",
          "prefix": "/usr/local",
          "files": {
            "catalina": {
              "url": "https://homebrew.bintray.com/bottles/dep-0.5.4.catalina.bottle.tar.gz",
              "sha256": "326ba98bcef16dc8823dd9fe76657e6ff0088a0669c0f857a05dd51867220bb7"
            },
            "mojave": {
              "url": "https://homebrew.bintray.com/bottles/dep-0.5.4.mojave.bottle.tar.gz",
              "sha256": "33200b5422fac00416ac44c7c28ad5aa627b845cd4d9aeb7002f7d41304deab0"
            },
            "high_sierra": {
              "url": "https://homebrew.bintray.com/bottles/dep-0.5.4.high_sierra.bottle.tar.gz",
              "sha256": "29cfe5b8c29bfbb09a93087dfbd30a9894ed596d3a4219072f022a001d2975cd"
            },
            "sierra": {
              "url": "https://homebrew.bintray.com/bottles/dep-0.5.4.sierra.bottle.tar.gz",
              "sha256": "ef9a0a978cbf2d4e537d21c4ff7b89a75b66228697b0aa348daa2284bc7362a9"
            }
          }
        }
      },
      "elixir": {
        "version": "1.9.4",
        "bottle": {
          "cellar": ":any_skip_relocation",
          "prefix": "/usr/local",
          "files": {
            "catalina": {
              "url": "https://homebrew.bintray.com/bottles/elixir-1.9.4.catalina.bottle.tar.gz",
              "sha256": "cc27b1d278293c48c4ffaa8c845a1c0b3dffc346e3de3fcab5f38f0468d12a9c"
            },
            "mojave": {
              "url": "https://homebrew.bintray.com/bottles/elixir-1.9.4.mojave.bottle.tar.gz",
              "sha256": "b265e0fa289d4e0bdd6d3c5833804410094b0e92b50657b151dbad7ba0427ee7"
            },
            "high_sierra": {
              "url": "https://homebrew.bintray.com/bottles/elixir-1.9.4.high_sierra.bottle.tar.gz",
              "sha256": "53e9755a828a0f7f6cf5abcd3d72cb74cecd90ad1cccc552dcbd34b03e68ace8"
            }
          }
        }
      },
      "ffmpeg": {
        "version": "4.2.1_2",
        "bottle": {
          "cellar": "/usr/local/Cellar",
          "prefix": "/usr/local",
          "files": {
            "catalina": {
              "url": "https://homebrew.bintray.com/bottles/ffmpeg-4.2.1_2.catalina.bottle.tar.gz",
              "sha256": "11b16a8f9657e0826774d41133052b088f778a50f6f8037f641923cbb6b90335"
            },
            "mojave": {
              "url": "https://homebrew.bintray.com/bottles/ffmpeg-4.2.1_2.mojave.bottle.tar.gz",
              "sha256": "a8dfa8eb401973fb9aa2adf806fca3e2a091ccb16d1270b5dcd67283022ba05b"
            },
            "high_sierra": {
              "url": "https://homebrew.bintray.com/bottles/ffmpeg-4.2.1_2.high_sierra.bottle.tar.gz",
              "sha256": "67fa397296c48e8f838a4cfbd654da8888a7e579eb53bda46e2d2ca70908d14e"
            }
          }
        }
      },
      "fzf": {
        "version": "0.19.0",
        "bottle": {
          "cellar": ":any_skip_relocation",
          "prefix": "/usr/local",
          "files": {
            "catalina": {
              "url": "https://homebrew.bintray.com/bottles/fzf-0.19.0.catalina.bottle.tar.gz",
              "sha256": "0be169ab230f6ff7b2322ee3d61fa0cd44e04300b688d207b67e910d948af442"
            },
            "mojave": {
              "url": "https://homebrew.bintray.com/bottles/fzf-0.19.0.mojave.bottle.tar.gz",
              "sha256": "5b5f429819576c27bab7bb658e3a99ae8043535e19d887fd9eaee954667ee715"
            },
            "high_sierra": {
              "url": "https://homebrew.bintray.com/bottles/fzf-0.19.0.high_sierra.bottle.tar.gz",
              "sha256": "19e9ba86b09129e06530b322f892ba89fb1db3173219ca0228cc0fe2d8281fbc"
            }
          }
        }
      },
      "git": {
        "version": "2.24.1",
        "bottle": {
          "cellar": "/usr/local/Cellar",
          "prefix": "/usr/local",
          "files": {
            "catalina": {
              "url": "https://homebrew.bintray.com/bottles/git-2.24.1.catalina.bottle.tar.gz",
              "sha256": "2779f9cea861ef4d906093ac7b7255b3eeb7b6f76cbbc8407035bd3d3b80305d"
            },
            "mojave": {
              "url": "https://homebrew.bintray.com/bottles/git-2.24.1.mojave.bottle.tar.gz",
              "sha256": "423599ea4d93020e4ee33965bf53c0e629c1d5a16e59efc657b4c914d9f52bd0"
            },
            "high_sierra": {
              "url": "https://homebrew.bintray.com/bottles/git-2.24.1.high_sierra.bottle.tar.gz",
              "sha256": "ce56a6b4012a93bfee18cc5017788033c423bef5f732f3117dfa59b688b08b5c"
            }
          }
        }
      },
      "git-lfs": {
        "version": "2.8.0",
        "bottle": {
          "cellar": ":any_skip_relocation",
          "prefix": "/usr/local",
          "files": {
            "mojave": {
              "url": "https://homebrew.bintray.com/bottles/git-lfs-2.8.0.mojave.bottle.tar.gz",
              "sha256": "1dfa249482bce6cdbfc46d6d34e88afd4fc7947dd98d4072b5c6c8909a31b03c"
            },
            "high_sierra": {
              "url": "https://homebrew.bintray.com/bottles/git-lfs-2.8.0.high_sierra.bottle.tar.gz",
              "sha256": "1ea60ee3dffe2ce7af00768361dbd4b2783d2159b7b269960d8504b0ab05c3a6"
            },
            "sierra": {
              "url": "https://homebrew.bintray.com/bottles/git-lfs-2.8.0.sierra.bottle.tar.gz",
              "sha256": "5f4a9d27c5d73aea0c8cb4ed403e15df4885d7aac44fec4d3fee1a82779c6a05"
            }
          }
        }
      },
      "htop": {
        "version": "2.2.0_1",
        "bottle": {
          "cellar": ":any",
          "prefix": "/usr/local",
          "files": {
            "catalina": {
              "url": "https://homebrew.bintray.com/bottles/htop-2.2.0_1.catalina.bottle.tar.gz",
              "sha256": "c06ff60960f64f5c8395f53d7419cbcce2a22ee87f0cb0138352c8a88111d21c"
            },
            "mojave": {
              "url": "https://homebrew.bintray.com/bottles/htop-2.2.0_1.mojave.bottle.tar.gz",
              "sha256": "77aa302765353b4085dcad52356d3264183e06310dda8d5bac64642299ea2902"
            },
            "high_sierra": {
              "url": "https://homebrew.bintray.com/bottles/htop-2.2.0_1.high_sierra.bottle.tar.gz",
              "sha256": "0ebfb655b91566ba31f8effc94d642a43305ff95bdc9b30b46fadc132e2ced0c"
            },
            "sierra": {
              "url": "https://homebrew.bintray.com/bottles/htop-2.2.0_1.sierra.bottle.tar.gz",
              "sha256": "ed93b86f011de155c5d261b8c9cc9cb81fd0017667bf3ebe26ee090716bcd650"
            }
          }
        }
      },
      "httpie": {
        "version": "1.0.3",
        "bottle": {
          "cellar": ":any_skip_relocation",
          "prefix": "/usr/local",
          "files": {
            "catalina": {
              "url": "https://homebrew.bintray.com/bottles/httpie-1.0.3.catalina.bottle.tar.gz",
              "sha256": "641b4d390468b8759f0b43a5f30074a680bbe61d71be201b7f7a48f7e497bd20"
            },
            "mojave": {
              "url": "https://homebrew.bintray.com/bottles/httpie-1.0.3.mojave.bottle.tar.gz",
              "sha256": "2436432e8ee1efe7f6c19c501af35aba453dabe3b9a9f88bed4e22a795bc6d1c"
            },
            "high_sierra": {
              "url": "https://homebrew.bintray.com/bottles/httpie-1.0.3.high_sierra.bottle.tar.gz",
              "sha256": "e50d67eb555607a235a14ee0c80e484c08295aed71fb82dad4ef9afc4af1c9b7"
            },
            "sierra": {
              "url": "https://homebrew.bintray.com/bottles/httpie-1.0.3.sierra.bottle.tar.gz",
              "sha256": "153ce88d4496d04fa1ba61641841b2c89254687af8c7e9aca7127b298e3ee0f1"
            }
          }
        }
      },
      "hugo": {
        "version": "0.61.0",
        "bottle": {
          "cellar": ":any_skip_relocation",
          "prefix": "/usr/local",
          "files": {
            "catalina": {
              "url": "https://homebrew.bintray.com/bottles/hugo-0.61.0.catalina.bottle.tar.gz",
              "sha256": "ffb3e8c81f9a1b76deea15d0578103f977d480e6d5df8cc4192c81de59dbe6ed"
            },
            "mojave": {
              "url": "https://homebrew.bintray.com/bottles/hugo-0.61.0.mojave.bottle.tar.gz",
              "sha256": "b10b5de8ecb0f7fa89a7c64b267a15ac080fc963afb090950d3e27f9ff5936e8"
            },
            "high_sierra": {
              "url": "https://homebrew.bintray.com/bottles/hugo-0.61.0.high_sierra.bottle.tar.gz",
              "sha256": "0c31ac21fd9a18e35c18c84644efa27e55eec372acc05175c65eed261de32f17"
            }
          }
        }
      },
      "kubernetes-cli": {
        "version": "1.17.0",
        "bottle": {
          "cellar": ":any_skip_relocation",
          "prefix": "/usr/local",
          "files": {
            "catalina": {
              "url": "https://homebrew.bintray.com/bottles/kubernetes-cli-1.17.0.catalina.bottle.tar.gz",
              "sha256": "ae55e2c178b7ccd8dc7811060ee179c8117241dc0d548dee35e3471c7bd90acb"
            },
            "mojave": {
              "url": "https://homebrew.bintray.com/bottles/kubernetes-cli-1.17.0.mojave.bottle.tar.gz",
              "sha256": "1901ca30376d47345bcbd2362a96745975dce03120e98f4641081b704d220652"
            },
            "high_sierra": {
              "url": "https://homebrew.bintray.com/bottles/kubernetes-cli-1.17.0.high_sierra.bottle.tar.gz",
              "sha256": "b790e7db7e9b6a6ae50423d076d07e8366bf4fb988550f3a3272343173166ff7"
            }
          }
        }
      },
      "kubernetes-helm": {
        "version": "2.16.1",
        "bottle": {
          "cellar": ":any_skip_relocation",
          "prefix": "/usr/local",
          "files": {
            "catalina": {
              "url": "https://homebrew.bintray.com/bottles/kubernetes-helm-2.16.1.catalina.bottle.tar.gz",
              "sha256": "e13b6d2b1a76b4af452e8582f2d2b07cde2b231de00ce16be04dbbf0c77b49af"
            },
            "mojave": {
              "url": "https://homebrew.bintray.com/bottles/kubernetes-helm-2.16.1.mojave.bottle.tar.gz",
              "sha256": "e41f332120fc3a047b2b654a6afb286c9a09e24a0ac5929ba943cc94940d1267"
            },
            "high_sierra": {
              "url": "https://homebrew.bintray.com/bottles/kubernetes-helm-2.16.1.high_sierra.bottle.tar.gz",
              "sha256": "29683ee842eaebd7a88c8c1f9e9069c12f6c8c0b531ff9255fe97330da58d2d8"
            }
          }
        }
      },
      "minikube": {
        "version": "1.6.1",
        "bottle": {
          "cellar": ":any_skip_relocation",
          "prefix": "/usr/local",
          "files": {
            "catalina": {
              "url": "https://homebrew.bintray.com/bottles/minikube-1.6.1.catalina.bottle.tar.gz",
              "sha256": "e596dcf8e632ede9c7fcdc603220b2d639f7863bf374c4f5efc9e0313590a700"
            },
            "mojave": {
              "url": "https://homebrew.bintray.com/bottles/minikube-1.6.1.mojave.bottle.tar.gz",
              "sha256": "a7dc8c21dc0552fd7c85334a31ff151d47205434e634a7346f85ac00aee0f204"
            },
            "high_sierra": {
              "url": "https://homebrew.bintray.com/bottles/minikube-1.6.1.high_sierra.bottle.tar.gz",
              "sha256": "07f995b5d3311834671fc4cb2d6ad54fde5feb236b9343bcedaff5fd945a5ca1"
            }
          }
        }
      },
      "neofetch": {
        "version": "6.1.0",
        "bottle": {
          "cellar": ":any_skip_relocation",
          "prefix": "/usr/local",
          "files": {
            "catalina": {
              "url": "https://homebrew.bintray.com/bottles/neofetch-6.1.0.catalina.bottle.tar.gz",
              "sha256": "d78734c76762358086f2e84b0f44aa6b55f7e7dc1d23e9254d764901a1547c28"
            },
            "mojave": {
              "url": "https://homebrew.bintray.com/bottles/neofetch-6.1.0.mojave.bottle.tar.gz",
              "sha256": "28101b31f5b5c74332f425dc22819ea272f085b73a7d8aa892daa8c9f12c3baf"
            },
            "high_sierra": {
              "url": "https://homebrew.bintray.com/bottles/neofetch-6.1.0.high_sierra.bottle.tar.gz",
              "sha256": "28101b31f5b5c74332f425dc22819ea272f085b73a7d8aa892daa8c9f12c3baf"
            },
            "sierra": {
              "url": "https://homebrew.bintray.com/bottles/neofetch-6.1.0.sierra.bottle.tar.gz",
              "sha256": "4f9522500f193bb660a7a449706417e450a8a217e98b6439c1c7a9deab3e0970"
            }
          }
        }
      },
      "neovim": {
        "version": "0.4.3",
        "bottle": {
          "cellar": "/usr/local/Cellar",
          "prefix": "/usr/local",
          "files": {
            "catalina": {
              "url": "https://homebrew.bintray.com/bottles/neovim-0.4.3.catalina.bottle.tar.gz",
              "sha256": "389ab254794ea04df8a106bf281c227c4fdee27c609d52951f32b9a0239031d6"
            },
            "mojave": {
              "url": "https://homebrew.bintray.com/bottles/neovim-0.4.3.mojave.bottle.tar.gz",
              "sha256": "fb6cc38c45be4650a4a750a314cec27f6f7643dc7c22a1f5abae347e1b39b388"
            },
            "high_sierra": {
              "url": "https://homebrew.bintray.com/bottles/neovim-0.4.3.high_sierra.bottle.tar.gz",
              "sha256": "b2f7450e005f4eb22bfaf650fe7741fa8629393a947b4dd48c9f91e7fc258113"
            }
          }
        }
      },
      "nvm": {
        "version": "0.35.1",
        "bottle": false
      },
      "php": {
        "version": "7.4.0",
        "bottle": {
          "cellar": "/usr/local/Cellar",
          "prefix": "/usr/local",
          "files": {
            "catalina": {
              "url": "https://homebrew.bintray.com/bottles/php-7.4.0.catalina.bottle.tar.gz",
              "sha256": "292d6dfec4f46c9b53a78f9f47833e026611778ebb7f615230e266d63cf74172"
            },
            "mojave": {
              "url": "https://homebrew.bintray.com/bottles/php-7.4.0.mojave.bottle.tar.gz",
              "sha256": "e8852cbaa0493683e53eb8897c1d165e7156479310c8d2490573a0029cbe0e40"
            },
            "high_sierra": {
              "url": "https://homebrew.bintray.com/bottles/php-7.4.0.high_sierra.bottle.tar.gz",
              "sha256": "6fb3529dbd8780d33f2fc7a4929dbf4b35cc2330dec6c02adc666e9c9924838e"
            }
          }
        }
      },
      "pipenv": {
        "version": "2018.11.26_2",
        "bottle": {
          "cellar": ":any_skip_relocation",
          "prefix": "/usr/local",
          "files": {
            "catalina": {
              "url": "https://homebrew.bintray.com/bottles/pipenv-2018.11.26_2.catalina.bottle.1.tar.gz",
              "sha256": "8f084160ecf6fec95317a0a298242040590ded00f5d375796c28697f1e9507c8"
            },
            "mojave": {
              "url": "https://homebrew.bintray.com/bottles/pipenv-2018.11.26_2.mojave.bottle.1.tar.gz",
              "sha256": "df13002254ad48b6586ed47c9c754992dbf669ce630b6c6c90ceca0a79c21e17"
            },
            "high_sierra": {
              "url": "https://homebrew.bintray.com/bottles/pipenv-2018.11.26_2.high_sierra.bottle.1.tar.gz",
              "sha256": "41aec81be5fa304ba9cfe4a061ac9088f6d51fac05bc0c6b73afddec431c6bb1"
            },
            "sierra": {
              "url": "https://homebrew.bintray.com/bottles/pipenv-2018.11.26_2.sierra.bottle.1.tar.gz",
              "sha256": "d961acb64dbd94b43950f877ce48e0bf519c07b71eed0188acdf81d55876d75c"
            }
          }
        }
      },
      "pyenv": {
        "version": "1.2.15",
        "bottle": {
          "cellar": ":any",
          "prefix": "/usr/local",
          "files": {
            "catalina": {
              "url": "https://homebrew.bintray.com/bottles/pyenv-1.2.15.catalina.bottle.tar.gz",
              "sha256": "b3a2c8756d697a74b665aa9e3a2e41abc991f592640492dec99afe1eef0878c2"
            },
            "mojave": {
              "url": "https://homebrew.bintray.com/bottles/pyenv-1.2.15.mojave.bottle.tar.gz",
              "sha256": "ab7e341286ec746f5f286284ad18703be8197810de374674297ec860c6c4dc00"
            },
            "high_sierra": {
              "url": "https://homebrew.bintray.com/bottles/pyenv-1.2.15.high_sierra.bottle.tar.gz",
              "sha256": "4a65548a46397a568717557cd7b012feeb4660391e8b8dcfa5d503cfb448f6ca"
            }
          }
        }
      },
      "rbenv": {
        "version": "1.1.2",
        "bottle": {
          "cellar": ":any",
          "prefix": "/usr/local",
          "files": {
            "catalina": {
              "url": "https://homebrew.bintray.com/bottles/rbenv-1.1.2.catalina.bottle.tar.gz",
              "sha256": "503ed6d818502f00f031b9f49461934e252b9bfba2876e90a326fc27bb1052d6"
            },
            "mojave": {
              "url": "https://homebrew.bintray.com/bottles/rbenv-1.1.2.mojave.bottle.tar.gz",
              "sha256": "d1019098dee8d037587069398e5ad04e6d736f834dc44ae73943bec46b10b260"
            },
            "high_sierra": {
              "url": "https://homebrew.bintray.com/bottles/rbenv-1.1.2.high_sierra.bottle.tar.gz",
              "sha256": "b5984102794a9d39388ca1f6ec77965aeea29b971cc00cb5af8ede8ee6c926d6"
            },
            "sierra": {
              "url": "https://homebrew.bintray.com/bottles/rbenv-1.1.2.sierra.bottle.tar.gz",
              "sha256": "873175a851e5aa4f5b3438072030b945c252f08a9a07760c64dc045e2cce4724"
            }
          }
        }
      },
      "sox": {
        "version": "14.4.2_3",
        "bottle": {
          "cellar": ":any",
          "prefix": "/usr/local",
          "files": {
            "catalina": {
              "url": "https://homebrew.bintray.com/bottles/sox-14.4.2_3.catalina.bottle.tar.gz",
              "sha256": "fc412be07e577c2161763dfb509f4fb43f4fe3bca206a1b0b370687df0a264fa"
            },
            "mojave": {
              "url": "https://homebrew.bintray.com/bottles/sox-14.4.2_3.mojave.bottle.tar.gz",
              "sha256": "4906207f83bd0f4ea1a67d040891711e9a9e8830216e451072f2957ca566b83d"
            },
            "high_sierra": {
              "url": "https://homebrew.bintray.com/bottles/sox-14.4.2_3.high_sierra.bottle.tar.gz",
              "sha256": "c0bb4ba7ec922d9a8c71c2ba84e28c66c67e4fdeae970011ea45e937f43c18bd"
            },
            "sierra": {
              "url": "https://homebrew.bintray.com/bottles/sox-14.4.2_3.sierra.bottle.tar.gz",
              "sha256": "dc8c294bb96c0b7ebc3ade73476c6031664bb8e81a32ece87ce84f815deeced5"
            }
          }
        }
      },
      "tree": {
        "version": "1.8.0",
        "bottle": {
          "cellar": ":any_skip_relocation",
          "prefix": "/usr/local",
          "files": {
            "catalina": {
              "url": "https://homebrew.bintray.com/bottles/tree-1.8.0.catalina.bottle.tar.gz",
              "sha256": "18f7984bdbab22251e9fc3c7832dbace5c7f7a77e8d63717bb0078385e2bf255"
            },
            "mojave": {
              "url": "https://homebrew.bintray.com/bottles/tree-1.8.0.mojave.bottle.tar.gz",
              "sha256": "7152288c457dd893de50fa9d6ac9a8599748564e1b3586eec8eff7057089051a"
            },
            "high_sierra": {
              "url": "https://homebrew.bintray.com/bottles/tree-1.8.0.high_sierra.bottle.tar.gz",
              "sha256": "107d965994381d34e90b58a62f1c306c1b8a698db2696cdd905ba65c801ecc3b"
            },
            "sierra": {
              "url": "https://homebrew.bintray.com/bottles/tree-1.8.0.sierra.bottle.tar.gz",
              "sha256": "07d980571469a0cc699c69a8726eee338f782ba61c041e58f01ddb2924d08aeb"
            }
          }
        }
      },
      "vim": {
        "version": "8.2.0",
        "bottle": {
          "cellar": "/usr/local/Cellar",
          "prefix": "/usr/local",
          "files": {
            "catalina": {
              "url": "https://homebrew.bintray.com/bottles/vim-8.2.0.catalina.bottle.tar.gz",
              "sha256": "2acaae2121e4d2e8356532b38c9d661b15a9fb0e0bb909a4e68dd7a1cdd399e4"
            },
            "mojave": {
              "url": "https://homebrew.bintray.com/bottles/vim-8.2.0.mojave.bottle.tar.gz",
              "sha256": "c9414649c775937aef44e7e050c9daeb8315b4bcb53e5c44610f06e1dd0260a2"
            },
            "high_sierra": {
              "url": "https://homebrew.bintray.com/bottles/vim-8.2.0.high_sierra.bottle.tar.gz",
              "sha256": "ad72c9418717e63037f39d13aa9629aed0aba0d846c41505024c2f68488ffd03"
            }
          }
        }
      },
      "wget": {
        "version": "1.20.3_2",
        "bottle": {
          "cellar": "/usr/local/Cellar",
          "prefix": "/usr/local",
          "files": {
            "catalina": {
              "url": "https://homebrew.bintray.com/bottles/wget-1.20.3_2.catalina.bottle.tar.gz",
              "sha256": "ef65c759c5097a36323fa9c77756468649e8d1980a3a4e05695c05e39568967c"
            },
            "mojave": {
              "url": "https://homebrew.bintray.com/bottles/wget-1.20.3_2.mojave.bottle.tar.gz",
              "sha256": "28f4090610946a4eb207df102d841de23ced0d06ba31cb79e040d883906dcd4f"
            },
            "high_sierra": {
              "url": "https://homebrew.bintray.com/bottles/wget-1.20.3_2.high_sierra.bottle.tar.gz",
              "sha256": "91dd0caca9bd3f38c439d5a7b6f68440c4274945615fae035ff0a369264b8a2f"
            }
          }
        }
      },
      "yarn": {
        "version": "1.21.1",
        "bottle": false
      },
      "youtube-dl": {
        "version": "2019.11.28",
        "bottle": false
      },
      "zlib": {
        "version": "1.2.11",
        "bottle": {
          "cellar": ":any",
          "prefix": "/usr/local",
          "files": {
            "catalina": {
              "url": "https://homebrew.bintray.com/bottles/zlib-1.2.11.catalina.bottle.tar.gz",
              "sha256": "8ec66cf6faa310712767efc3022fdd16568a79234439f64bf579acb628f893bc"
            },
            "mojave": {
              "url": "https://homebrew.bintray.com/bottles/zlib-1.2.11.mojave.bottle.tar.gz",
              "sha256": "245a43a59c57f83848e7382974bb80a46eac1d53bcaefb1bdebd1f85107d4169"
            },
            "high_sierra": {
              "url": "https://homebrew.bintray.com/bottles/zlib-1.2.11.high_sierra.bottle.tar.gz",
              "sha256": "30548658b43cf66979f2756680fbb32d3c19c967e478ceea22d07f536b22bbce"
            },
            "sierra": {
              "url": "https://homebrew.bintray.com/bottles/zlib-1.2.11.sierra.bottle.tar.gz",
              "sha256": "f822b4dbab4a15b889316b89248c7b4d15d6af9dc460bf209b9425b0accb7fa3"
            },
            "el_capitan": {
              "url": "https://homebrew.bintray.com/bottles/zlib-1.2.11.el_capitan.bottle.tar.gz",
              "sha256": "3f912f6f1ce6c586128ebde29756c883b89409e652ca7aa9a29a773c2d4d0915"
            },
            "yosemite": {
              "url": "https://homebrew.bintray.com/bottles/zlib-1.2.11.yosemite.bottle.tar.gz",
              "sha256": "5b969eb38b90a3e31869586df9d62e59d359212b16c6a270aee690dd67caa491"
            }
          }
        }
      },
      "zsh": {
        "version": "5.7.1",
        "bottle": {
          "cellar": "/usr/local/Cellar",
          "prefix": "/usr/local",
          "files": {
            "catalina": {
              "url": "https://homebrew.bintray.com/bottles/zsh-5.7.1.catalina.bottle.tar.gz",
              "sha256": "a24afee5cc1af2b139b6afb8963992b3fb22a4b9fbfa02402ac17e6bfa66a27a"
            },
            "mojave": {
              "url": "https://homebrew.bintray.com/bottles/zsh-5.7.1.mojave.bottle.tar.gz",
              "sha256": "793d87f67e64a5e01dfdea890af218e4779a2df514d395b956e464129af16fd7"
            },
            "high_sierra": {
              "url": "https://homebrew.bintray.com/bottles/zsh-5.7.1.high_sierra.bottle.tar.gz",
              "sha256": "6656fe9aa5d5cbaff49bc9c1ccf17b7d96d21036ac44c9181bd35c57dc38b450"
            },
            "sierra": {
              "url": "https://homebrew.bintray.com/bottles/zsh-5.7.1.sierra.bottle.tar.gz",
              "sha256": "008dfc844b88fcd61925233b08f0d78b2851bf2901320a5f6ee975da4b8604e3"
            }
          }
        }
      },
      "helm": {
        "version": "3.0.1",
        "bottle": {
          "cellar": ":any_skip_relocation",
          "prefix": "/usr/local",
          "files": {
            "catalina": {
              "url": "https://homebrew.bintray.com/bottles/helm-3.0.1.catalina.bottle.tar.gz",
              "sha256": "ea598eaa6bd98765f32d556b700d80b18e0cadec0b378b1c12f02f2602d5983a"
            },
            "mojave": {
              "url": "https://homebrew.bintray.com/bottles/helm-3.0.1.mojave.bottle.tar.gz",
              "sha256": "b981fac0003ad39b7a4f187563ccb5668e52272146745a1a315e5f794ee19271"
            },
            "high_sierra": {
              "url": "https://homebrew.bintray.com/bottles/helm-3.0.1.high_sierra.bottle.tar.gz",
              "sha256": "312e69ab0ecaff681f03d69d975456e670ba4c9331ae43d60c5b75c8f868790f"
            }
          }
        }
      },
      "composer": {
        "version": "1.9.1",
        "bottle": false
      },
      "helm@2": {
        "version": "2.16.1",
        "bottle": {
          "cellar": ":any_skip_relocation",
          "prefix": "/usr/local",
          "files": {
            "catalina": {
              "url": "https://homebrew.bintray.com/bottles/helm@2-2.16.1.catalina.bottle.tar.gz",
              "sha256": "1450f1bdc13f6ac6f08c3edcefbdf0301a73d6158a8335b3fec68c32bf367d7c"
            },
            "mojave": {
              "url": "https://homebrew.bintray.com/bottles/helm@2-2.16.1.mojave.bottle.tar.gz",
              "sha256": "eedc16bde2576c3ddb4d02213154ad09951e5e65ec2d1a1ec1e451d6fa5108b2"
            },
            "high_sierra": {
              "url": "https://homebrew.bintray.com/bottles/helm@2-2.16.1.high_sierra.bottle.tar.gz",
              "sha256": "c9d3fe248f6231c860f7cc0226bea285284f7a8af82ee5d2d88e35c9c407fb0f"
            }
          }
        }
      }
    },
    "cask": {
      "adobe-creative-cloud": {
        "version": "latest"
      },
      "appcleaner": {
        "version": "3.5"
      },
      "bitwarden": {
        "version": "1.16.6"
      },
      "coconutbattery": {
        "version": "3.8.2"
      },
      "colorsnapper": {
        "version": "1.6.0"
      },
      "cyberduck": {
        "version": "7.1.2.31675"
      },
      "dashlane": {
        "version": "6.1948.0.27265"
      },
      "dbeaver-community": {
        "version": "6.3.0"
      },
      "docker": {
        "version": "2.1.0.4,39773"
      },
      "firefox": {
        "version": "70.0.1"
      },
      "firefox-developer-edition": {
        "version": "latest"
      },
      "goland": {
        "version": "2019.2.3,192.6817.25"
      },
      "google-chat": {
        "version": "19.9.101"
      },
      "google-chrome": {
        "version": "78.0.3904.87"
      },
      "insomnia": {
        "version": "7.0.3"
      },
      "iterm2": {
        "version": "3.3.6"
      },
      "java": {
        "version": "13.0.1,9:cec27d702aa74d5a8630c65ae61e4305"
      },
      "kap": {
        "version": "2.2.0"
      },
      "keybase": {
        "version": "4.7.2-20191026044208,6fc2e969b4"
      },
      "sequel-pro": {
        "version": "1.1.2"
      },
      "slack": {
        "version": "4.1.2"
      },
      "spotify": {
        "version": "latest"
      },
      "the-unarchiver": {
        "version": "4.1.0,121:1549634528"
      },
      "transmission": {
        "version": "2.94"
      },
      "vagrant": {
        "version": "2.2.6"
      },
      "virtualbox": {
        "version": "6.1.0,135406"
      },
      "visual-studio-code": {
        "version": "1.39.2"
      },
      "vlc": {
        "version": "3.0.8"
      },
      "postman": {
        "version": "7.11.0"
      },
      "fly": {
        "version": "5.7.0"
      },
      "jetbrains-toolbox": {
        "version": "1.16.6207"
      }
    }
  },
  "system": {
    "macos": {
      "catalina": {
        "HOMEBREW_VERSION": "2.2.1",
        "HOMEBREW_PREFIX": "/usr/local",
        "Homebrew/homebrew-core": "92825ca1a32fcc1ce50ba280ecd87ec3f31809f1",
        "CLT": "11.2.0.0.1.1571444319",
        "Xcode": "11.2.1",
        "macOS": "10.15.1"
      }
    }
  }
}